{
  "main": {
    "id": "50f4611ff2f5de0a",
    "type": "split",
    "children": [
      {
        "id": "9fa4edd179974acd",
        "type": "tabs",
        "children": [
          {
            "id": "f45619208928840c",
            "type": "leaf",
            "state": {
              "type": "markdown",
              "state": {
                "file": "Process/Journal.md",
                "mode": "source",
                "source": false
              },
              "icon": "lucide-file",
              "title": "Journal"
            }
          }
        ]
      }
    ],
    "direction": "vertical"
  },
  "left": {
    "id": "9982135b024cfb29",
    "type": "split",
    "children": [
      {
        "id": "f5bc6f35b8f0d69f",
        "type": "tabs",
        "children": [
          {
            "id": "5154e789214887ac",
            "type": "leaf",
            "state": {
              "type": "file-explorer",
              "state": {
                "sortOrder": "alphabetical",
                "autoReveal": false
              },
              "icon": "lucide-folder-closed",
              "title": "Files"
            }
          },
          {
            "id": "2879065fcec35018",
            "type": "leaf",
            "state": {
              "type": "search",
              "state": {
                "query": "",
                "matchingCase": false,
                "explainSearch": false,
                "collapseAll": false,
                "extraContext": false,
                "sortOrder": "alphabetical"
              },
              "icon": "lucide-search",
              "title": "Search"
            }
          },
          {
            "id": "71dfc1a78c9fcbbf",
            "type": "leaf",
            "state": {
              "type": "bookmarks",
              "state": {},
              "icon": "lucide-bookmark",
              "title": "Bookmarks"
            }
          }
        ]
      }
    ],
    "direction": "horizontal",
    "width": 300
  },
  "right": {
    "id": "f65e50b4a2539876",
    "type": "split",
    "children": [
      {
        "id": "ec7e5ee39f18e89e",
        "type": "tabs",
        "children": [
          {
            "id": "0a06f33b3303ccd9",
            "type": "leaf",
            "state": {
              "type": "backlink",
              "state": {
                "file": "README.md",
                "collapseAll": false,
                "extraContext": false,
                "sortOrder": "alphabetical",
                "showSearch": false,
                "searchQuery": "",
                "backlinkCollapsed": false,
                "unlinkedCollapsed": true
              },
              "icon": "links-coming-in",
              "title": "Backlinks for README"
            }
          },
          {
            "id": "9f9ec322604aded0",
            "type": "leaf",
            "state": {
              "type": "outgoing-link",
              "state": {
                "file": "README.md",
                "linksCollapsed": false,
                "unlinkedCollapsed": true
              },
              "icon": "links-going-out",
              "title": "Outgoing links from README"
            }
          },
          {
            "id": "3dca1b77b3f334d4",
            "type": "leaf",
            "state": {
              "type": "tag",
              "state": {
                "sortOrder": "frequency",
                "useHierarchy": true,
                "showSearch": false,
                "searchQuery": ""
              },
              "icon": "lucide-tags",
              "title": "Tags"
            }
          },
          {
            "id": "42fbd824c46c5530",
            "type": "leaf",
            "state": {
              "type": "outline",
              "state": {
                "file": "README.md",
                "followCursor": false,
                "showSearch": false,
                "searchQuery": ""
              },
              "icon": "lucide-list",
              "title": "Outline of README"
            }
          }
        ]
      }
    ],
    "direction": "horizontal",
    "width": 300,
    "collapsed": true
  },
  "left-ribbon": {
    "hiddenItems": {
      "switcher:Open quick switcher": false,
      "graph:Open graph view": false,
      "canvas:Create new canvas": false,
      "daily-notes:Open today's daily note": false,
      "templates:Insert template": false,
      "command-palette:Open command palette": false,
      "bases:Create new base": false
    }
  },
  "active": "f45619208928840c",
  "lastOpenFiles": [
    "Temp/ADB-Refresh0d33ee5539e6847cdaf964a7feb47180",
    "().md",
    "Process/Journal.md",
    "Temp/ADB-Refreshe380bab018da24db8ba7b60817c53519",
    "Process/Media/pinkTriangles.gif",
    "Process/Media/ScreenRecording2025-10-11at15.17.48-ezgif.com-video-to-gif-converter.gif",
    "Process/Media/pinkTriangles.png",
    "Process/Media/tris.png",
    "Process/Media/Screenshot 2025-10-11 at 15.20.25.png",
    "Library/Artifacts/10/1052631ea7228a62841404589717237f",
    "Library/Artifacts/91/91fe5086e35101a529fe840587e96e4a",
    "Temp/ADB-Refresh9793d5ca2ea4b46398f14c1b5f29153a",
    "Library/Artifacts/95/9526ef89100ce992390157606c2b335f",
    "Library/Artifacts/0d/0d0a6fc9f50a7091aeda0affb463d226",
    "Temp/ADB-Refreshd5e17e1553d074dffaf28780f9a8a255",
    "Temp/ADB-Refresh1e392532818c948ab874b580b6c7cf2e",
    "Temp/ADB-Refresh8d361e1c7a7404e65984240ef8911cfe",
    "Library/Artifacts/50/50b1f6a46638f23a3f39b2357c5c8638",
    "Assets/Sprites/triangle.png",
    "Assets/Sprites/triangle.png.jpg",
    "Process/Media/sphereInteraction.gif",
    "Process/Media/ScreenRecording2025-10-10at09.41.25-ezgif.com-video-to-gif-converter.gif",
    "Assets/Resources/paperWaterSprites/layer_5/30.png",
    "Tools/venv/lib/python3.13/site-packages/numpy/random/LICENSE.md",
    "README_frame_extractor.md",
    "README.md"
  ]
}